linkedin_python/__init__.py
linkedin_python/api.py
linkedin_python/schemas.py
linkedin_python/user.py
linkedin_python-0.0.1.dist-info/METADATA
linkedin_python-0.0.1.dist-info/WHEEL
linkedin_python-0.0.1.dist-info/top_level.txt
linkedin_python-0.0.1.dist-info/RECORD
